setup.py
pystream/__init__.py
pystream/main.py
pystream.egg-info/PKG-INFO
pystream.egg-info/SOURCES.txt
pystream.egg-info/dependency_links.txt
pystream.egg-info/entry_points.txt
pystream.egg-info/requires.txt
pystream.egg-info/top_level.txt