Metadata-Version: 1.1
Name: pystream
Version: 0.1
Summary: Stream uploads/downloads to/from S3 easily with smart_open
Home-page: http://github.com/EverythingMe/pystream
Author: EverythingMe
Author-email: omrib@everything.me
License: UNKNOWN
Platform: UNKNOWN
Classifier: Development Status :: 5 - Production/Stable
Classifier: Environment :: Console
Classifier: Intended Audience :: Developers
Classifier: Intended Audience :: System Administrators
Classifier: Operating System :: OS Independent
Classifier: Programming Language :: Python :: 2.7
Classifier: Topic :: System :: Clustering
Classifier: Topic :: System :: Systems Administration
Classifier: Topic :: Utilities
